odoo/addons/mgmtsystem_action_hazard/README.rst
odoo/addons/mgmtsystem_action_hazard/__init__.py
odoo/addons/mgmtsystem_action_hazard/__manifest__.py
odoo/addons/mgmtsystem_action_hazard/i18n/it.po
odoo/addons/mgmtsystem_action_hazard/i18n/mgmtsystem_action_hazard.pot
odoo/addons/mgmtsystem_action_hazard/models/__init__.py
odoo/addons/mgmtsystem_action_hazard/models/mgmtsystem_action.py
odoo/addons/mgmtsystem_action_hazard/models/mgmtsystem_hazard.py
odoo/addons/mgmtsystem_action_hazard/readme/CONTRIBUTORS.rst
odoo/addons/mgmtsystem_action_hazard/readme/DESCRIPTION.rst
odoo/addons/mgmtsystem_action_hazard/readme/USAGE.rst
odoo/addons/mgmtsystem_action_hazard/static/description/icon.png
odoo/addons/mgmtsystem_action_hazard/static/description/icon.png.oca
odoo/addons/mgmtsystem_action_hazard/static/description/index.html
odoo/addons/mgmtsystem_action_hazard/views/mgmtsystem_action.xml
odoo/addons/mgmtsystem_action_hazard/views/mgmtsystem_hazard.xml
odoo_addon_mgmtsystem_action_hazard-16.0.1.0.0.4.dist-info/METADATA
odoo_addon_mgmtsystem_action_hazard-16.0.1.0.0.4.dist-info/WHEEL
odoo_addon_mgmtsystem_action_hazard-16.0.1.0.0.4.dist-info/top_level.txt
odoo_addon_mgmtsystem_action_hazard-16.0.1.0.0.4.dist-info/RECORD
